wlanpass/__init__.py
wlanpass/getwifipass.py
WlanPass-0.0.4.dist-info/LICENSE
WlanPass-0.0.4.dist-info/METADATA
WlanPass-0.0.4.dist-info/WHEEL
WlanPass-0.0.4.dist-info/top_level.txt
WlanPass-0.0.4.dist-info/RECORD
